AirzoneCloud/AirzoneCloud.py
AirzoneCloud/Device.py
AirzoneCloud/System.py
AirzoneCloud/Zone.py
AirzoneCloud/__init__.py
AirzoneCloud/contants.py
AirzoneCloud-0.1.0.dist-info/LICENSE
AirzoneCloud-0.1.0.dist-info/METADATA
AirzoneCloud-0.1.0.dist-info/WHEEL
AirzoneCloud-0.1.0.dist-info/top_level.txt
AirzoneCloud-0.1.0.dist-info/RECORD
